Resources/Example Verilog Project/example_2.v
module example_2(
			input wire [2:0] opc, 
			input wire [3:0] a,
			input wire [3:0] b,
			output wire [7:0] c
			);
	assign c = opc == 3'b000 ? a + b: // if opc = 0 then a+b. 
			   opc == 3'b001 ? a - b: // if opc = 1 then a-b. 
							 a * b;  // if opc = 2 then a*b.
endmodule

Resources/Example Verilog Project/example_3.v
module example_3(
			input wire [2:0] opc, 
			input wire [3:0] a,
			input wire [3:0] b,
			output wire [7:0] c
			);
	assign c = opc == 3'b011 ? a == b: // 3 is equal to
			   opc == 3'b100 ? a < b:  // 4 is less than 
			   opc == 3'b101 ? a <= b: // 5 is less than or equal
			   opc == 3'b110 ? a > b:  // 6 is greater than 
						       a >= b; // 7 is greater than or equal 
endmodule

Resources/Example Verilog Project/example_1.v
module example_1(
			input wire clk,
			input wire [2:0] opc, //0, 1, 2 are alu. 3, 4, 5, 6, 7
			input wire [3:0] a,
			input wire [3:0] b,
			output reg [7:0] c
			);
			
	wire [7:0] c_ex2;
	wire [7:0] c_ex3;
	// We use dataflow style in the instances so having 
	// the output be a reg doesn't work.
	
	example_3 ex_3(.opc(opc), .a(a), .b(b), .c(c_ex3)); 
	// Comparison module.
	
	example_2 ex_2(.opc(opc), .a(a), .b(b), .c(c_ex2));
	// Alu module.
	
	always@(posedge clk) begin
		if (opc > 2) // Goes to greater, less, equal 
			c <= c_ex3;
		else begin // Goes to math. 
			c <= c_ex2;
		end
	end
endmodule

Resources/Example Verilog Project/example_tb.v
`timescale 1ps/1ps
module example_tb;
	reg clk; 
	reg [2:0]opc; 
	// Opcodes less than 3 are alu tasks.
	// Otherwise they are comparison tasks (less, greater). 
	reg [3:0]a;
	// First condition. 
	reg [3:0]b;
	// Second condition. 
	wire [7:0]c;
	// Output condition. 
	
	example_1 ex_1 (.clk(clk), .opc(opc), .a(a), .b(b), .c(c));
	// Creates an instance of the actual verilog code. 
	
	always #1 clk = ~clk; // This is a clock generator.
	
	// This tests all opcodes with 3 sets of the inputs. 
	
	initial begin
		$dumpfile("example.vcd");
		$dumpvars(0, example_tb);
		clk = 0; 
		
		opc = 0;
		a = 1; b = 0; 
		#2
		a = 0; b = 1;
		#2
		a = 1; b = 1;
		#2
		
		opc = 1;
		a = 1; b = 0; 
		#2
		a = 0; b = 1; // If the output number is negative it wraps around. 
		#2
		a = 1; b = 1;
		#2
		
		opc = 2;
		a = 1; b = 0; 
		#2
		a = 0; b = 1;
		#2
		a = 1; b = 1;
		#2
		
		opc = 3;
		a = 1; b = 0; 
		#2
		a = 0; b = 1;
		#2
		a = 1; b = 1;
		#2
		
		opc = 4;
		a = 1; b = 0; 
		#2
		a = 0; b = 1;
		#2
		a = 1; b = 1;
		#2
		
		opc = 5;
		a = 1; b = 0; 
		#2
		a = 0; b = 1;
		#2
		a = 1; b = 1;
		#2
		
		opc = 6;
		a = 1; b = 0; 
		#2
		a = 0; b = 1;
		#2
		a = 1; b = 1;
		#2
		
		opc = 7;
		a = 1; b = 0; 
		#2
		a = 0; b = 1;
		#2
		a = 1; b = 1;
		#2
		$finish;
	end
endmodule

Resources/Example Verilog Project/example.vcd
$date
	Mon Nov 24 12:24:11 2025
$end
$version
	Icarus Verilog
$end
$timescale
	1ps
$end
$scope module example_tb $end
$var wire 8 ! c [7:0] $end
$var reg 4 " a [3:0] $end
$var reg 4 # b [3:0] $end
$var reg 1 $ clk $end
$var reg 3 % opc [2:0] $end
$scope module ex_1 $end
$var wire 4 & a [3:0] $end
$var wire 4 ' b [3:0] $end
$var wire 8 ( c_ex2 [7:0] $end
$var wire 8 ) c_ex3 [7:0] $end
$var wire 1 * clk $end
$var wire 3 + opc [2:0] $end
$var reg 8 , c [7:0] $end
$scope module ex_3 $end
$var wire 4 - a [3:0] $end
$var wire 4 . b [3:0] $end
$var wire 8 / c [7:0] $end
$var wire 3 0 opc [2:0] $end
$upscope $end
$scope module ex_2 $end
$var wire 4 1 a [3:0] $end
$var wire 4 2 b [3:0] $end
$var wire 8 3 c [7:0] $end
$var wire 3 4 opc [2:0] $end
$upscope $end
$upscope $end
$upscope $end
$enddefinitions $end
#0
$dumpvars
b0 4
b1 3
b0 2
b1 1
b0 0
b1 /
b0 .
b1 -
bx ,
b0 +
0*
b1 )
b1 (
b0 '
b1 &
b0 %
0$
b0 #
b1 "
bx !
$end
#1
b1 ,
b1 !
1$
1*
#2
b0 )
b0 /
0$
0*
b1 #
b1 '
b1 .
b1 2
b0 "
b0 &
b0 -
b0 1
#3
1$
1*
#4
b1 )
b1 /
b10 (
b10 3
0$
0*
b1 "
b1 &
b1 -
b1 1
#5
b10 ,
b10 !
1$
1*
#6
b1 (
b1 3
0$
0*
b0 #
b0 '
b0 .
b0 2
b1 %
b1 +
b1 0
b1 4
#7
b1 ,
b1 !
1$
1*
#8
b0 )
b0 /
b11111111 (
b11111111 3
0$
0*
b1 #
b1 '
b1 .
b1 2
b0 "
b0 &
b0 -
b0 1
#9
b11111111 ,
b11111111 !
1$
1*
#10
b1 )
b1 /
b0 (
b0 3
0$
0*
b1 "
b1 &
b1 -
b1 1
#11
b0 ,
b0 !
1$
1*
#12
0$
0*
b0 #
b0 '
b0 .
b0 2
b10 %
b10 +
b10 0
b10 4
#13
1$
1*
#14
b0 )
b0 /
0$
0*
b1 #
b1 '
b1 .
b1 2
b0 "
b0 &
b0 -
b0 1
#15
1$
1*
#16
b1 )
b1 /
b1 (
b1 3
0$
0*
b1 "
b1 &
b1 -
b1 1
#17
b1 ,
b1 !
1$
1*
#18
b0 (
b0 3
b0 )
b0 /
0$
0*
b0 #
b0 '
b0 .
b0 2
b11 %
b11 +
b11 0
b11 4
#19
b0 ,
b0 !
1$
1*
#20
0$
0*
b1 #
b1 '
b1 .
b1 2
b0 "
b0 &
b0 -
b0 1
#21
1$
1*
#22
b1 (
b1 3
b1 )
b1 /
0$
0*
b1 "
b1 &
b1 -
b1 1
#23
b1 ,
b1 !
1$
1*
#24
b0 (
b0 3
b0 )
b0 /
0$
0*
b0 #
b0 '
b0 .
b0 2
b100 %
b100 +
b100 0
b100 4
#25
b0 ,
b0 !
1$
1*
#26
b1 )
b1 /
0$
0*
b1 #
b1 '
b1 .
b1 2
b0 "
b0 &
b0 -
b0 1
#27
b1 ,
b1 !
1$
1*
#28
b0 )
b0 /
b1 (
b1 3
0$
0*
b1 "
b1 &
b1 -
b1 1
#29
b0 ,
b0 !
1$
1*
#30
b0 (
b0 3
0$
0*
b0 #
b0 '
b0 .
b0 2
b101 %
b101 +
b101 0
b101 4
#31
1$
1*
#32
b1 )
b1 /
0$
0*
b1 #
b1 '
b1 .
b1 2
b0 "
b0 &
b0 -
b0 1
#33
b1 ,
b1 !
1$
1*
#34
b1 (
b1 3
0$
0*
b1 "
b1 &
b1 -
b1 1
#35
1$
1*
#36
b0 (
b0 3
0$
0*
b0 #
b0 '
b0 .
b0 2
b110 %
b110 +
b110 0
b110 4
#37
1$
1*
#38
b0 )
b0 /
0$
0*
b1 #
b1 '
b1 .
b1 2
b0 "
b0 &
b0 -
b0 1
#39
b0 ,
b0 !
1$
1*
#40
b1 (
b1 3
0$
0*
b1 "
b1 &
b1 -
b1 1
#41
1$
1*
#42
b1 )
b1 /
b0 (
b0 3
0$
0*
b0 #
b0 '
b0 .
b0 2
b111 %
b111 +
b111 0
b111 4
#43
b1 ,
b1 !
1$
1*
#44
b0 )
b0 /
0$
0*
b1 #
b1 '
b1 .
b1 2
b0 "
b0 &
b0 -
b0 1
#45
b0 ,
b0 !
1$
1*
#46
b1 )
b1 /
b1 (
b1 3
0$
0*
b1 "
b1 &
b1 -
b1 1
#47
b1 ,
b1 !
1$
1*
